.gitignore
.travis.yml
CHANGES.txt
CONTRIBUTORS.txt
MANIFEST.in
MultiLingualCarouselExample.rst
README.rst
bootstrap.py
buildout.cfg
i18n.cfg
setup.py
test-plone-3.3.x.cfg
test-plone-4.3.x.cfg
travis-4.0.x.cfg
travis-4.1.x.cfg
travis-4.2.x.cfg
travis-4.3.x.cfg
Products/__init__.py
Products.Carousel.egg-info/PKG-INFO
Products.Carousel.egg-info/SOURCES.txt
Products.Carousel.egg-info/dependency_links.txt
Products.Carousel.egg-info/entry_points.txt
Products.Carousel.egg-info/namespace_packages.txt
Products.Carousel.egg-info/not-zip-safe
Products.Carousel.egg-info/requires.txt
Products.Carousel.egg-info/top_level.txt
Products/Carousel/__init__.py
Products/Carousel/config.py
Products/Carousel/configure.zcml
Products/Carousel/interfaces.py
Products/Carousel/menu.zcml
Products/Carousel/meta.py
Products/Carousel/meta.zcml
Products/Carousel/setuphandlers.py
Products/Carousel/upgrades.py
Products/Carousel/upgrades.zcml
Products/Carousel/usei18ndude.sh
Products/Carousel/utils.py
Products/Carousel/version.txt
Products/Carousel/vocabularies.py
Products/Carousel/Extensions/Install.py
Products/Carousel/analytics/__init__.py
Products/Carousel/analytics/banner.pt
Products/Carousel/analytics/configure.zcml
Products/Carousel/analytics/tracking.py
Products/Carousel/browser/__init__.py
Products/Carousel/browser/carousel.css
Products/Carousel/browser/carousel.js
Products/Carousel/browser/configure.zcml
Products/Carousel/browser/folder.py
Products/Carousel/browser/manager.py
Products/Carousel/browser/settings.pt
Products/Carousel/browser/viewlet.pt
Products/Carousel/browser/viewlet.py
Products/Carousel/browser/templates/banner-base.pt
Products/Carousel/browser/templates/banner-default.pt
Products/Carousel/browser/templates/pager-base.pt
Products/Carousel/browser/templates/pager-classic.pt
Products/Carousel/browser/templates/pager-none.pt
Products/Carousel/browser/templates/pager-numbers.pt
Products/Carousel/browser/templates/pager-prevnext.pt
Products/Carousel/browser/templates/pager-titles.pt
Products/Carousel/content/__init__.py
Products/Carousel/content/carouselbanner.py
Products/Carousel/content/configure.zcml
Products/Carousel/i18n/Products.Carousel-plone-da.po
Products/Carousel/i18n/Products.Carousel-plone-de.po
Products/Carousel/i18n/Products.Carousel-plone-es.po
