Metadata-Version: 1.1
Name: Products.Carousel
Version: 3.0.2
Summary: Carousel allows you to add user-configurable rotating banners to any section of a Plone site.
Home-page: https://github.com/collective/Products.Carousel
Author: Groundwire
Author-email: davidglick@groundwire.org
License: GPL
Keywords: plone carousel slideshow banners rotating features
Platform: UNKNOWN
Classifier: Framework :: Plone
Classifier: Framework :: Plone :: 4.0
Classifier: Framework :: Plone :: 4.1
Classifier: Framework :: Plone :: 4.2
Classifier: Framework :: Plone :: 4.3
Classifier: Intended Audience :: Developers
Classifier: Topic :: Software Development :: Libraries :: Python Modules
Classifier: License :: OSI Approved :: GNU General Public License (GPL)
Classifier: Development Status :: 5 - Production/Stable
Classifier: Programming Language :: Python
Classifier: Programming Language :: Python :: 2.6
Classifier: Programming Language :: Python :: 2.7
